overload_numpy/__init__.py
overload_numpy/_typeutils.py
overload_numpy/constraints.py
overload_numpy/mixin.py
overload_numpy/overload.py
overload_numpy/py.typed
overload_numpy/utils.py
overload_numpy/implementors/__init__.py
overload_numpy/implementors/dispatch.py
overload_numpy/implementors/func.py
overload_numpy/implementors/many.py
overload_numpy/implementors/ufunc.py
overload_numpy-0.1.0.dist-info/AUTHORS.rst
overload_numpy-0.1.0.dist-info/LICENSE
overload_numpy-0.1.0.dist-info/METADATA
overload_numpy-0.1.0.dist-info/WHEEL
overload_numpy-0.1.0.dist-info/top_level.txt
overload_numpy-0.1.0.dist-info/RECORD
