Metadata-Version: 2.1
Name: overload_numpy
Version: 0.1.0
Summary: Overload NumPy Functions
Author-email: Nathaniel Starkman <n.starkman@mail.utoronto.ca>
Maintainer-email: Nathaniel Starkman <n.starkman@mail.utoronto.ca>
License: BSD 3-Clause License
Project-URL: homepage, https://overload_numpy.readthedocs.io
Project-URL: repository, https://github.com/nstarman/overload_numpy
Project-URL: documentation, https://overload_numpy.readthedocs.io
Keywords: numpy,interoperability
Classifier: Intended Audience :: Science/Research
Classifier: Intended Audience :: Developers
Classifier: License :: OSI Approved :: BSD License
Classifier: Operating System :: OS Independent
Classifier: Programming Language :: Python :: 3
Requires-Python: >=3.8
Provides-Extra: all
Provides-Extra: test
Provides-Extra: docs
License-File: LICENSE
License-File: AUTHORS.rst
